Metadata-Version: 2.1
Name: pyjellyfish
Version: 1.3.1
Summary: Python interface to the Jellfish DNA k-mer counter
Author-email: Albert Feghaly <albert.feghaly@umontreal.ca>
License: BSD-3-Clause
Project-URL: Repository, https://github.com/iric-soft/pyJellyfish
Keywords: k-mer,DNA,RNA
Classifier: Development Status :: 5 - Production/Stable
Classifier: Intended Audience :: Science/Research
Classifier: Intended Audience :: Developers
Classifier: Intended Audience :: Healthcare Industry
Classifier: Topic :: Scientific/Engineering :: Bio-Informatics
Classifier: Topic :: Software Development :: Build Tools
Classifier: Programming Language :: Python :: 3
Classifier: Programming Language :: Python :: 3.8
Classifier: Programming Language :: Python :: 3.9
Classifier: Programming Language :: Python :: 3.10
Classifier: Programming Language :: Python :: 3.11
Classifier: Programming Language :: Python :: 3.12
Classifier: Operating System :: MacOS
Classifier: Operating System :: POSIX :: Linux
Classifier: License :: OSI Approved :: BSD License
Classifier: Natural Language :: English
Requires-Python: >=3.8
License-File: LICENSE
